spin_and_heave-3.2.0.dist-info/licenses/LICENSE
spinandheave/__init__.py
spinandheave/main.py
spinandheave/scripts/__init__.py
spinandheave/scripts/build.sh
spin_and_heave-3.2.0.dist-info/METADATA
spin_and_heave-3.2.0.dist-info/WHEEL
spin_and_heave-3.2.0.dist-info/entry_points.txt
spin_and_heave-3.2.0.dist-info/top_level.txt
spin_and_heave-3.2.0.dist-info/RECORD
