Metadata-Version: 2.4
Name: spin-and-heave
Version: 3.2.0
Summary: package and zip lambdas then run terraform.
Home-page: https://gitlab.com/shindagger/spin-and-heave
Author: Andy Klier, Gus Clemens
Author-email: andyklier@gmail.com
License: MIT
Classifier: Programming Language :: Python :: 3
Classifier: Operating System :: OS Independent
License-File: LICENSE
Requires-Dist: setuptools
Dynamic: author
Dynamic: author-email
Dynamic: classifier
Dynamic: description
Dynamic: description-content-type
Dynamic: home-page
Dynamic: license
Dynamic: license-file
Dynamic: requires-dist
Dynamic: summary
